{
  "schema": "roguelike_card_game.encounters.v1",
  "content_version": "mvp.1.1-trimmed",
  "items": [
    {
      "id": "encounter.mvp.normal_01",
      "node_type": "normal",
      "enemies": [
        { "instance_id": "enemy_01", "enemy_id": "enemy.training_dummy" }
      ],
      "reward_profile": {
        "card_pack_ids": [],
        "relic_id": null
      },
      "teaching_goal_key": "encounter.mvp.normal_01.goal",
      "difficulty_note": "Single-target teaching fight for action cards, beat targeting, and colorless energy."
    },
    {
      "id": "encounter.mvp.normal_03",
      "node_type": "normal",
      "enemies": [
        { "instance_id": "enemy_01", "enemy_id": "enemy.splitling" },
        { "instance_id": "enemy_02", "enemy_id": "enemy.splitling" }
      ],
      "reward_profile": {
        "card_pack_ids": [],
        "relic_id": null
      },
      "teaching_goal_key": "encounter.mvp.normal_03.goal",
      "difficulty_note": "Multi-target teaching fight for target choice and all-enemy finishers."
    },
    {
      "id": "encounter.mvp.boss_01",
      "node_type": "boss",
      "enemies": [
        { "instance_id": "enemy_01", "enemy_id": "enemy.black_tower_warden" }
      ],
      "reward_profile": {
        "card_pack_ids": [],
        "relic_id": null
      },
      "teaching_goal_key": "encounter.mvp.boss_01.goal",
      "difficulty_note": "Final MVP check for three-beat planning, defense, colorless energy, and finishers."
    }
  ]
}
